Workbook

Sheet Profitability_Working_Data
A1: Record_ID | B1: Month | C1: Product | D1: Region | E1: Sales_Units | F1: Selling_Price_per_Unit | G1: Material_Cost_per_Unit | H1: Labour_Cost_per_Unit | I1: Overhead_per_Unit | J1: Revenue | K1: Material_Cost | L1: Labour_Cost | M1: Overhead_Cost | N1: Total_Cost | O1: Unit_Cost | P1: Gross_Profit | Q1: Unit_Profit | R1: Margin_%
A2: 1 | B2: Jan-2023 | C2: Gears | D2: North | E2: 715 | F2: 500 | G2: 230 | H2: 55 | I2: 25 | J2: 357500 | K2: 164450 | L2: 39325 | M2: 17875 | N2: 221650 | O2: 310 | P2: 135850 | Q2: 190 | R2: 0.38
A3: 2 | B3: Jan-2023 | C3: Shafts | D3: North | E3: 667 | F3: 450 | G3: 220 | H3: 50 | I3: 22 | J3: 300150 | K3: 146740 | L3: 33350 | M3: 14674 | N3: 194764 | O3: 292 | P3: 105386 | Q3: 158 | R3: 0.35111111
A4: 3 | B4: Jan-2023 | C4: Bearings | D4: North | E4: 676 | F4: 400 | G4: 210 | H4: 48 | I4: 20 | J4: 270400 | K4: 141960 | L4: 32448 | M4: 13520 | N4: 187928 | O4: 278 | P4: 82472 | Q4: 122 | R4: 0.305
A5: 4 | B5: Jan-2023 | C5: Gears | D5: South | E5: 647 | F5: 500 | G5: 230 | H5: 55 | I5: 25 | J5: 323500 | K5: 148810 | L5: 35585 | M5: 16175 | N5: 200570 | O5: 310 | P5: 122930 | Q5: 190 | R5: 0.38
A6: 5 | B6: Jan-2023 | C6: Shafts | D6: South | E6: 603 | F6: 450 | G6: 220 | H6: 50 | I6: 22 | J6: 271350 | K6: 132660 | L6: 30150 | M6: 13266 | N6: 176076 | O6: 292 | P6: 95274 | Q6: 158 | R6: 0.35111111
A7: 6 | B7: Jan-2023 | C7: Bearings | D7: South | E7: 612 | F7: 400 | G7: 210 | H7: 48 | I7: 20 | J7: 244800 | K7: 128520 | L7: 29376 | M7: 12240 | N7: 170136 | O7: 278 | P7: 74664 | Q7: 122 | R7: 0.305
A8: 7 | B8: Jan-2023 | C8: Gears | D8: West | E8: 681 | F8: 500 | G8: 230 | H8: 55 | I8: 25 | J8: 340500 | K8: 156630 | L8: 37455 | M8: 17025 | N8: 211110 | O8: 310 | P8: 129390 | Q8: 190 | R8: 0.38
A9: 8 | B9: Jan-2023 | C9: Shafts | D9: West | E9: 635 | F9: 450 | G9: 220 | H9: 50 | I9: 22 | J9: 285750 | K9: 139700 | L9: 31750 | M9: 13970 | N9: 185420 | O9: 292 | P9: 100330 | Q9: 158 | R9: 0.35111111
A10: 9 | B10: Jan-2023 | C10: Bearings | D10: West | E10: 644 | F10: 400 | G10: 210 | H10: 48 | I10: 20 | J10: 257600 | K10: 135240 | L10: 30912 | M10: 12880 | N10: 179032 | O10: 278 | P10: 78568 | Q10: 122 | R10: 0.305
A11: 10 | B11: Feb-2023 | C11: Gears | D11: North | E11: 746 | F11: 500 | G11: 230 | H11: 55 | I11: 25 | J11: 373000 | K11: 171580 | L11: 41030 | M11: 18650 | N11: 231260 | O11: 310 | P11: 141740 | Q11: 190 | R11: 0.38
A12: 11 | B12: Feb-2023 | C12: Shafts | D12: North | E12: 696 | F12: 450 | G12: 220 | H12: 50 | I12: 22 | J12: 313200 | K12: 153120 | L12: 34800 | M12: 15312 | N12: 203232 | O12: 292 | P12: 109968 | Q12: 158 | R12: 0.35111111
A13: 12 | B13: Feb-2023 | C13: Bearings | D13: North | E13: 706 | F13: 400 | G13: 210 | H13: 48 | I13: 20 | J13: 282400 | K13: 148260 | L13: 33888 | M13: 14120 | N13: 196268 | O13: 278 | P13: 86132 | Q13: 122 | R13: 0.305
... A55: 54 | B55: Jun-2023 | C55: Bearings | D55: West | E55: 784 | F55: 400 | G55: 210 | H55: 48 | I55: 20 | J55: 313600 | K55: 164640 | L55: 37632 | M55: 15680 | N55: 217952 | O55: 278 | P55: 95648 | Q55: 122 | R55: 0.305

Sheet Unit_Cost_Working
A1: Product | B1: Sales Units | C1: Total Cost / Unit | D1: Gross Profit / Unit | E1: Check: Unit Cost + Unit Profit | F1: Revenue / Unit | G1: Margin %
A2: Gears | B2: =SUMIF(Profitability_Working_Data!$C$2:$C$55,A2,Profitability_Working_Data!$E$2:$E$55) | C2: =SUMIF(Profitability_Working_Data!$C$2:$C$55,A2,Profitability_Working_Data!$N$2:$N$55)/B2 | D2: =SUMIF(Profitability_Working_Data!$C$2:$C$55,A2,Profitability_Working_Data!$P$2:$P$55)/B2 | E2: =C2+D2 | F2: =SUMIF(Profitability_Working_Data!$C$2:$C$55,A2,Profitability_Working_Data!$J$2:$J$55)/SUMIF(Profitability_Working_Data!$C$2:$C$55,A2,Profitability_Working_Data!$E$2:$E$55) | G2: =SUMIF(Profitability_Working_Data!$C$2:$C$55,A2,Profitability_Working_Data!$P$2:$P$55)/SUMIF(Profitability_Working_Data!$C$2:$C$55,A2,Profitability_Working_Data!$J$2:$J$55)
A3: Shafts | B3: =SUMIF(Profitability_Working_Data!$C$2:$C$55,A3,Profitability_Working_Data!$E$2:$E$55) | C3: =SUMIF(Profitability_Working_Data!$C$2:$C$55,A3,Profitability_Working_Data!$N$2:$N$55)/B3 | D3: =SUMIF(Profitability_Working_Data!$C$2:$C$55,A3,Profitability_Working_Data!$P$2:$P$55)/B3 | E3: =C3+D3 | F3: =SUMIF(Profitability_Working_Data!$C$2:$C$55,A3,Profitability_Working_Data!$J$2:$J$55)/SUMIF(Profitability_Working_Data!$C$2:$C$55,A3,Profitability_Working_Data!$E$2:$E$55) | G3: =SUMIF(Profitability_Working_Data!$C$2:$C$55,A3,Profitability_Working_Data!$P$2:$P$55)/SUMIF(Profitability_Working_Data!$C$2:$C$55,A3,Profitability_Working_Data!$J$2:$J$55)
A4: Bearings | B4: =SUMIF(Profitability_Working_Data!$C$2:$C$55,A4,Profitability_Working_Data!$E$2:$E$55) | C4: =SUMIF(Profitability_Working_Data!$C$2:$C$55,A4,Profitability_Working_Data!$N$2:$N$55)/B4 | D4: =SUMIF(Profitability_Working_Data!$C$2:$C$55,A4,Profitability_Working_Data!$P$2:$P$55)/B4 | E4: =C4+D4 | F4: =SUMIF(Profitability_Working_Data!$C$2:$C$55,A4,Profitability_Working_Data!$J$2:$J$55)/SUMIF(Profitability_Working_Data!$C$2:$C$55,A4,Profitability_Working_Data!$E$2:$E$55) | G4: =SUMIF(Profitability_Working_Data!$C$2:$C$55,A4,Profitability_Working_Data!$P$2:$P$55)/SUMIF(Profitability_Working_Data!$C$2:$C$55,A4,Profitability_Working_Data!$J$2:$J$55)

Sheet Revenue_Working
A1: Product | B1: Sales Units | C1: Revenue | D1: Revenue / Unit
A2: Gears | B2: =SUMIF(Profitability_Working_Data!$C$2:$C$55,A2,Profitability_Working_Data!$E$2:$E$55) | C2: =SUMIF(Profitability_Working_Data!$C$2:$C$55,A2,Profitability_Working_Data!$J$2:$J$55) | D2: =C2/B2
A3: Shafts | B3: =SUMIF(Profitability_Working_Data!$C$2:$C$55,A3,Profitability_Working_Data!$E$2:$E$55) | C3: =SUMIF(Profitability_Working_Data!$C$2:$C$55,A3,Profitability_Working_Data!$J$2:$J$55) | D3: =C3/B3
A4: Bearings | B4: =SUMIF(Profitability_Working_Data!$C$2:$C$55,A4,Profitability_Working_Data!$E$2:$E$55) | C4: =SUMIF(Profitability_Working_Data!$C$2:$C$55,A4,Profitability_Working_Data!$J$2:$J$55) | D4: =C4/B4

Sheet Profit_Working
A1: Product | B1: Revenue | C1: Total Cost | D1: Gross Profit | E1: Margin % | F1: Unit Profit
A2: Gears | B2: =SUMIF(Profitability_Working_Data!$C$2:$C$55,A2,Profitability_Working_Data!$J$2:$J$55) | C2: =SUMIF(Profitability_Working_Data!$C$2:$C$55,A2,Profitability_Working_Data!$N$2:$N$55) | D2: =B2-C2 | E2: =D2/B2 | F2: =D2/SUMIF(Profitability_Working_Data!$C$2:$C$55,A2,Profitability_Working_Data!$E$2:$E$55)
A3: Shafts | B3: =SUMIF(Profitability_Working_Data!$C$2:$C$55,A3,Profitability_Working_Data!$J$2:$J$55) | C3: =SUMIF(Profitability_Working_Data!$C$2:$C$55,A3,Profitability_Working_Data!$N$2:$N$55) | D3: =B3-C3 | E3: =D3/B3 | F3: =D3/SUMIF(Profitability_Working_Data!$C$2:$C$55,A3,Profitability_Working_Data!$E$2:$E$55)
A4: Bearings | B4: =SUMIF(Profitability_Working_Data!$C$2:$C$55,A4,Profitability_Working_Data!$J$2:$J$55) | C4: =SUMIF(Profitability_Working_Data!$C$2:$C$55,A4,Profitability_Working_Data!$N$2:$N$55) | D4: =B4-C4 | E4: =D4/B4 | F4: =D4/SUMIF(Profitability_Working_Data!$C$2:$C$55,A4,Profitability_Working_Data!$E$2:$E$55)

Sheet Product_Profitability
A1: Product | B1: Sales_Units | C1: Revenue | D1: Material_Cost | E1: Labour_Cost | F1: Overhead_Cost | G1: Total_Cost | H1: Gross_Profit | I1: Unit_Cost | J1: Unit_Profit | K1: Margin_%
A2: Bearings | B2: 12852 | C2: 5140800 | D2: 2698920 | E2: 616896 | F2: 257040 | G2: 3572856 | H2: 1567944 | I2: 278 | J2: 122 | K2: 0.305
A3: Gears | B3: 13586 | C3: 6793000 | D3: 3124780 | E3: 747230 | F3: 339650 | G3: 4211660 | H3: 2581340 | I3: 310 | J3: 190 | K3: 0.38
A4: Shafts | B4: 12668 | C4: 5700600 | D4: 2786960 | E4: 633400 | F4: 278696 | G4: 3699056 | H4: 2001544 | I4: 292 | J4: 158 | K4: 0.35111111

Sheet Monthly_Profitability
A1: Month | B1: Sales_Units | C1: Revenue | D1: Total_Cost | E1: Gross_Profit | F1: Unit_Cost | G1: Unit_Profit | H1: Margin_%
A2: Jan-2023 | B2: 5880 | C2: 2651550 | D2: 1726686 | E2: 924864 | F2: 293.65408 | G2: 157.2898 | H2: 0.34880127
A3: Feb-2023 | B3: 6134 | C3: 2766050 | D3: 1801262 | E3: 964788 | F3: 293.6521 | G3: 157.2853 | H3: 0.3487963
A4: Mar-2023 | B4: 6390 | C4: 2881500 | D4: 1876440 | E4: 1005060 | F4: 293.65258 | G4: 157.28638 | H4: 0.3487975
A5: Apr-2023 | B5: 6646 | C5: 2996950 | D5: 1951618 | E5: 1045332 | F5: 293.65302 | G5: 157.28739 | H5: 0.34879861
A6: May-2023 | B6: 6900 | C6: 3111450 | D6: 2026194 | E6: 1085256 | F6: 293.6513 | G6: 157.28348 | H6: 0.34879429
A7: Jun-2023 | B7: 7156 | C7: 3226900 | D7: 2101372 | E7: 1125528 | F7: 293.65176 | G7: 157.28452 | H7: 0.34879544

Sheet Region_Profitability
A1: Region | B1: Sales_Units | C1: Revenue | D1: Total_Cost | E1: Gross_Profit | F1: Unit_Cost | G1: Unit_Profit | H1: Margin_%
A2: North | B2: 13686 | C2: 6171550 | D2: 4018930 | E2: 2152620 | F2: 293.65264 | G2: 157.28628 | H2: 0.3487973
A3: South | B3: 12384 | C3: 5584400 | D3: 3636584 | E3: 1947816 | F3: 293.65181 | G3: 157.28488 | H3: 0.34879593
A4: West | B4: 13036 | C4: 5878450 | D4: 3828058 | E4: 2050392 | F4: 293.65281 | G4: 157.2869 | H4: 0.34879807

Sheet Cost_Component_Analysis
A1: Product | B1: Material_Cost | C1: Labour_Cost | D1: Overhead_Cost | E1: Total_Cost
A2: Bearings | B2: 2698920 | C2: 616896 | D2: 257040 | E2: 3572856
A3: Gears | B3: 3124780 | C3: 747230 | D3: 339650 | E3: 4211660
A4: Shafts | B4: 2786960 | C4: 633400 | D4: 278696 | E4: 3699056

Sheet Profitability_Questions
A1: Question | B1: Expected Working
A2: 1. Which product has the highest gross profit per unit? | B2: Compare Unit Profit in Unit_Cost_Working.
A3: 2. How is unit cost calculated? | B3: Total Cost ÷ Sales Units.
A4: 3. How is unit profit calculated? | B4: Gross Profit ÷ Sales Units.
A5: 4. How is gross profit calculated? | B5: Revenue − Total Cost.
A6: 5. How is profit margin calculated? | B6: Gross Profit ÷ Revenue.
A7: 6. Which cost component is largest? | B7: Compare Material, Labour and Overhead Cost.
A8: 7. How can monthly profitability be reviewed? | B8: Compare Revenue, Total Cost, Gross Profit and Margin %.
A9: 8. Why can high revenue and high profit differ? | B9: Revenue and cost structures can differ by product.
A10: 9. What is the role of unit economics? | B10: It shows economics of one saleable unit.
A11: 10. What should be checked before a business conclusion? | B11: Units, prices, costs, formulas and data quality.

Sheet Business_Insights
A1: Metric / Insight | B1: Illustrative Result
A2: Dataset type | B2: Illustrative ACE Gears-style manufacturing dataset; not official IITM data.
A3: Observation period | B3: Jan-2023 to Jun-2023
A4: Products | B4: Gears, Shafts, Bearings
A5: Regions | B5: North, South, West
A6: Primary profitability flow | B6: Sales Units → Revenue → Total Cost → Gross Profit → Unit Profit → Margin %
A7: Largest cost component | B7: Material cost is the largest component in this illustrative dataset.
A8: Use of unit profitability | B8: Supports product-level comparison of revenue, cost and profit per unit.
A9: Interpretation caution | B9: These figures are for learning/practice, not real company performance.

Sheet Data_Dictionary
A1: Field | B1: Meaning | C1: Calculation / Source
A2: Record_ID | B2: Unique row identifier | C2: Sequential identifier
A3: Month | B3: Observation month | C3: Jan-2023 to Jun-2023
A4: Product | B4: Product category | C4: Gears / Shafts / Bearings
A5: Region | B5: Sales/operating region | C5: North / South / West
A6: Sales_Units | B6: Units sold | C6: Illustrative input
A7: Selling_Price_per_Unit | B7: Price per unit | C7: Illustrative input
A8: Revenue | B8: Sales value | C8: Sales Units × Selling Price per Unit
A9: Material_Cost | B9: Total material cost | C9: Sales Units × Material Cost per Unit
A10: Labour_Cost | B10: Total labour cost | C10: Sales Units × Labour Cost per Unit
A11: Overhead_Cost | B11: Total overhead cost | C11: Sales Units × Overhead per Unit
A12: Total_Cost | B12: Total modeled cost | C12: Material + Labour + Overhead
... A16: Margin_% | B16: Gross profit margin | C16: Gross Profit ÷ Revenue

Sheet Profitability_Working
A1: Step | B1: Formula / Working
A2: 1 | B2: Revenue = Sales Units × Selling Price per Unit
A3: 2 | B3: Material Cost = Sales Units × Material Cost per Unit
A4: 3 | B4: Labour Cost = Sales Units × Labour Cost per Unit
A5: 4 | B5: Overhead Cost = Sales Units × Overhead per Unit
A6: 5 | B6: Total Cost = Material Cost + Labour Cost + Overhead Cost
A7: 6 | B7: Unit Cost = Total Cost ÷ Sales Units
A8: 7 | B8: Gross Profit = Revenue − Total Cost
A9: 8 | B9: Unit Profit = Gross Profit ÷ Sales Units
A10: 9 | B10: Margin % = Gross Profit ÷ Revenue
A11: 10 | B11: Compare products using Unit Cost, Unit Profit and Margin %
A12: 11 | B12: Compare months using Revenue, Cost, Gross Profit and Margin %
A13: 12 | B13: Compare regions using the same profitability metrics

Sheet Instructions
A1: Section | B1: Instruction
A2: Objective | B2: Practice detailed unit-level profitability calculations.
A3: Workbook flow | B3: Start with Profitability_Working_Data and follow the working sheets.
A4: Formula practice | B4: Trace Revenue, Cost, Gross Profit, Unit Profit and Margin.
A5: Product analysis | B5: Use Product_Profitability and Profit_Working.
A6: Monthly analysis | B6: Use Monthly_Profitability for trend interpretation.
A7: Regional analysis | B7: Use Region_Profitability for regional comparison.
A8: Cost analysis | B8: Use Cost_Component_Analysis to inspect cost structure.
A9: Questions | B9: Complete Profitability_Questions without relying only on the dashboard.
A10: Important | B10: All dataset values are illustrative learning data.

Sheet Profitability_Dashboard
A1: Day 052 — Unit Level Profitability Working
A3: Illustrative dataset | Unit economics | Revenue | Cost | Gross Profit | Margin
