Workbook

Sheet ACE_Gears_Data
A1: Record_ID | B1: Product | C1: Region | D1: Customer_Type | E1: Production_Units | F1: Sales_Units | G1: Scrap_Units | H1: Revenue | I1: Production_Cost
A2: 1 | B2: Gears | C2: North | D2: OEM | E2: 1200 | F2: 950 | G2: 180 | H2: 72000 | I2: 68400
A3: 2 | B3: Gears | C3: South | D3: OEM | E3: 1350 | F3: 1100 | G3: 210 | H3: 81000 | I3: 77000
A4: 3 | B4: Gears | C4: West | D4: Distributor | E4: 980 | F4: 820 | G4: 145 | H4: 58800 | I4: 50840
A5: 4 | B5: Shafts | C5: North | D5: OEM | E5: 900 | F5: 760 | G5: 130 | H5: 54000 | I5: 57760
A6: 5 | B6: Shafts | C6: South | D6: Distributor | E6: 1050 | F6: 880 | G6: 160 | H6: 63000 | I6: 56320
A7: 6 | B7: Shafts | C7: West | D7: OEM | E7: 1120 | F7: 940 | G7: 175 | H7: 67200 | I7: 65800
A8: 7 | B8: Bearings | C8: North | D8: Distributor | E8: 1500 | F8: 1260 | G8: 220 | H8: 75000 | I8: 65520
A9: 8 | B9: Bearings | C9: South | D9: OEM | E9: 1650 | F9: 1400 | G9: 250 | H9: 82500 | I9: 80500
A10: 9 | B10: Bearings | C10: West | D10: Distributor | E10: 1380 | F10: 1160 | G10: 205 | H10: 69000 | I10: 59890
A11: 10 | B11: Gears | C11: North | D11: Distributor | E11: 1280 | F11: 1040 | G11: 195 | H11: 76800 | I11: 71760
A12: 11 | B12: Gears | C12: South | D12: OEM | E12: 1420 | F12: 1180 | G12: 225 | H12: 85200 | I12: 82600
A13: 12 | B13: Gears | C13: West | D13: OEM | E13: 1100 | F13: 920 | G13: 165 | H13: 66000 | I13: 60720
... A21: 20 | B21: Shafts | C21: South | D21: Distributor | E21: 1160 | F21: 950 | G21: 180 | H21: 69600 | I21: 61700

Sheet Case_Context
A1: Field | B1: Case Context
A2: Case | B2: ACE Gears manufacturing case introduction
A3: Business Area | B3: Manufacturing
A4: Primary Focus | B4: Product, revenue, production and regional performance
A5: Products | B5: Gears, Shafts, Bearings
A6: Regions | B6: North, South, West
A7: Customer Types | B7: OEM, Distributor
A8: Purpose | B8: Prepare the dataset and questions for detailed case analysis

Sheet Product_Summary
A1: Product | B1: Production Units | C1: Sales Units | D1: Scrap Units | E1: Revenue | F1: Production Cost | G1: Gross Margin | H1: Scrap Rate
A2: Gears | B2: =SUMIF(ACE_Gears_Data!$B$2:$B$21,A2,ACE_Gears_Data!$E$2:$E$21) | C2: =SUMIF(ACE_Gears_Data!$B$2:$B$21,A2,ACE_Gears_Data!$F$2:$F$21) | D2: =SUMIF(ACE_Gears_Data!$B$2:$B$21,A2,ACE_Gears_Data!$G$2:$G$21) | E2: =SUMIF(ACE_Gears_Data!$B$2:$B$21,A2,ACE_Gears_Data!$H$2:$H$21) | F2: =SUMIF(ACE_Gears_Data!$B$2:$B$21,A2,ACE_Gears_Data!$I$2:$I$21) | G2: =E2-F2 | H2: =D2/B2
A3: Shafts | B3: =SUMIF(ACE_Gears_Data!$B$2:$B$21,A3,ACE_Gears_Data!$E$2:$E$21) | C3: =SUMIF(ACE_Gears_Data!$B$2:$B$21,A3,ACE_Gears_Data!$F$2:$F$21) | D3: =SUMIF(ACE_Gears_Data!$B$2:$B$21,A3,ACE_Gears_Data!$G$2:$G$21) | E3: =SUMIF(ACE_Gears_Data!$B$2:$B$21,A3,ACE_Gears_Data!$H$2:$H$21) | F3: =SUMIF(ACE_Gears_Data!$B$2:$B$21,A3,ACE_Gears_Data!$I$2:$I$21) | G3: =E3-F3 | H3: =D3/B3
A4: Bearings | B4: =SUMIF(ACE_Gears_Data!$B$2:$B$21,A4,ACE_Gears_Data!$E$2:$E$21) | C4: =SUMIF(ACE_Gears_Data!$B$2:$B$21,A4,ACE_Gears_Data!$F$2:$F$21) | D4: =SUMIF(ACE_Gears_Data!$B$2:$B$21,A4,ACE_Gears_Data!$G$2:$G$21) | E4: =SUMIF(ACE_Gears_Data!$B$2:$B$21,A4,ACE_Gears_Data!$H$2:$H$21) | F4: =SUMIF(ACE_Gears_Data!$B$2:$B$21,A4,ACE_Gears_Data!$I$2:$I$21) | G4: =E4-F4 | H4: =D4/B4

Sheet Region_Summary
A1: Region | B1: Production Units | C1: Sales Units | D1: Scrap Units | E1: Revenue | F1: Production Cost | G1: Gross Margin | H1: Scrap Rate
A2: North | B2: =SUMIF(ACE_Gears_Data!$C$2:$C$21,A2,ACE_Gears_Data!$E$2:$E$21) | C2: =SUMIF(ACE_Gears_Data!$C$2:$C$21,A2,ACE_Gears_Data!$F$2:$F$21) | D2: =SUMIF(ACE_Gears_Data!$C$2:$C$21,A2,ACE_Gears_Data!$G$2:$G$21) | E2: =SUMIF(ACE_Gears_Data!$C$2:$C$21,A2,ACE_Gears_Data!$H$2:$H$21) | F2: =SUMIF(ACE_Gears_Data!$C$2:$C$21,A2,ACE_Gears_Data!$I$2:$I$21) | G2: =E2-F2 | H2: =D2/B2
A3: South | B3: =SUMIF(ACE_Gears_Data!$C$2:$C$21,A3,ACE_Gears_Data!$E$2:$E$21) | C3: =SUMIF(ACE_Gears_Data!$C$2:$C$21,A3,ACE_Gears_Data!$F$2:$F$21) | D3: =SUMIF(ACE_Gears_Data!$C$2:$C$21,A3,ACE_Gears_Data!$G$2:$G$21) | E3: =SUMIF(ACE_Gears_Data!$C$2:$C$21,A3,ACE_Gears_Data!$H$2:$H$21) | F3: =SUMIF(ACE_Gears_Data!$C$2:$C$21,A3,ACE_Gears_Data!$I$2:$I$21) | G3: =E3-F3 | H3: =D3/B3
A4: West | B4: =SUMIF(ACE_Gears_Data!$C$2:$C$21,A4,ACE_Gears_Data!$E$2:$E$21) | C4: =SUMIF(ACE_Gears_Data!$C$2:$C$21,A4,ACE_Gears_Data!$F$2:$F$21) | D4: =SUMIF(ACE_Gears_Data!$C$2:$C$21,A4,ACE_Gears_Data!$G$2:$G$21) | E4: =SUMIF(ACE_Gears_Data!$C$2:$C$21,A4,ACE_Gears_Data!$H$2:$H$21) | F4: =SUMIF(ACE_Gears_Data!$C$2:$C$21,A4,ACE_Gears_Data!$I$2:$I$21) | G4: =E4-F4 | H4: =D4/B4

Sheet Customer_Summary
A1: Customer Type | B1: Production Units | C1: Sales Units | D1: Revenue | E1: Gross Margin
A2: OEM | B2: =SUMIF(ACE_Gears_Data!$D$2:$D$21,A2,ACE_Gears_Data!$E$2:$E$21) | C2: =SUMIF(ACE_Gears_Data!$D$2:$D$21,A2,ACE_Gears_Data!$F$2:$F$21) | D2: =SUMIF(ACE_Gears_Data!$D$2:$D$21,A2,ACE_Gears_Data!$H$2:$H$21) | E2: =SUMIF(ACE_Gears_Data!$D$2:$D$21,A2,ACE_Gears_Data!$H$2:$H$21)-SUMIF(ACE_Gears_Data!$D$2:$D$21,A2,ACE_Gears_Data!$I$2:$I$21)
A3: Distributor | B3: =SUMIF(ACE_Gears_Data!$D$2:$D$21,A3,ACE_Gears_Data!$E$2:$E$21) | C3: =SUMIF(ACE_Gears_Data!$D$2:$D$21,A3,ACE_Gears_Data!$F$2:$F$21) | D3: =SUMIF(ACE_Gears_Data!$D$2:$D$21,A3,ACE_Gears_Data!$H$2:$H$21) | E3: =SUMIF(ACE_Gears_Data!$D$2:$D$21,A3,ACE_Gears_Data!$H$2:$H$21)-SUMIF(ACE_Gears_Data!$D$2:$D$21,A3,ACE_Gears_Data!$I$2:$I$21)

Sheet Case_Questions
A1: Question_ID | B1: Business Question | C1: Analysis
A2: 1 | B2: Which product generates the most revenue? | C2: Product summary
A3: 2 | B3: Which product has the highest sales volume? | C3: Product summary
A4: 3 | B4: Which region contributes the most revenue? | C4: Regional summary
A5: 4 | B5: How do OEM and Distributor customers compare? | C5: Customer summary
A6: 5 | B6: What is the relationship between production and sales? | C6: Production vs sales
A7: 6 | B7: Where is scrap rate relatively high? | C7: Product and region quality metrics
A8: 7 | B8: Which products should be examined further? | C8: Combine product and financial evidence

Sheet Data_Dictionary
A1: Field | B1: Meaning | C1: Type
A2: Record_ID | B2: Observation identifier | C2: Integer
A3: Product | B3: Manufactured product | C3: Category
A4: Region | B4: Business region | C4: Category
A5: Customer_Type | B5: Customer type | C5: Category
A6: Production_Units | B6: Units produced | C6: Numeric
A7: Sales_Units | B7: Units sold | C7: Numeric
A8: Scrap_Units | B8: Units classified as scrap | C8: Numeric
A9: Revenue | B9: Recorded revenue | C9: Numeric
A10: Production_Cost | B10: Recorded production cost | C10: Numeric

Sheet Business_Insights
A1: Area | B1: Case Learning
A2: Case Context | B2: ACE Gears is treated as a manufacturing-sector business case for analytical practice.
A3: Product View | B3: Product-level analysis helps compare output, sales, revenue and quality indicators.
A4: Regional View | B4: Regional analysis allows the same KPIs to be compared across business regions.
A5: Customer View | B5: OEM and Distributor groups provide a customer-type perspective.
A6: Quality View | B6: Scrap rate provides a simple way to compare production losses.
A7: Financial View | B7: Revenue, production cost and gross margin provide a basic financial view.
A8: Next Step | B8: The following case stages can use the prepared dataset for deeper analysis.

Sheet Instructions
A1: Step | B1: Instruction
A2: 1 | B2: Read Case_Context before analyzing the data.
A3: 2 | B3: Review the Data_Dictionary.
A4: 3 | B4: Inspect ACE_Gears_Data.
A5: 4 | B5: Review Product_Summary.
A6: 5 | B6: Review Region_Summary.
A7: 6 | B7: Review Customer_Summary.
A8: 7 | B8: Attempt the Case_Questions.
A9: 8 | B9: Use Business_Insights as learning guidance, not as a substitute for analysis.

Sheet ACE_Gears_Dashboard
A1: ACE GEARS CASE — INTRODUCTION DASHBOARD
A2: Day 039 | Product, regional and customer analysis
A4: Total Revenue | B4: =SUM(ACE_Gears_Data!H2:H21) | C4: Total Production | D4: =SUM(ACE_Gears_Data!E2:E21) | E4: Total Sales | F4: =SUM(ACE_Gears_Data!F2:F21)
A6: Product | B6: Revenue | C6: Region | D6: Revenue
A8: Gears | B8: =SUMIF(ACE_Gears_Data!$B$2:$B$21,A8,ACE_Gears_Data!$H$2:$H$21) | C8: North | D8: =SUMIF(ACE_Gears_Data!$C$2:$C$21,C8,ACE_Gears_Data!$H$2:$H$21)
A9: Shafts | B9: =SUMIF(ACE_Gears_Data!$B$2:$B$21,A9,ACE_Gears_Data!$H$2:$H$21) | C9: South | D9: =SUMIF(ACE_Gears_Data!$C$2:$C$21,C9,ACE_Gears_Data!$H$2:$H$21)
A10: Bearings | B10: =SUMIF(ACE_Gears_Data!$B$2:$B$21,A10,ACE_Gears_Data!$H$2:$H$21) | C10: West | D10: =SUMIF(ACE_Gears_Data!$C$2:$C$21,C10,ACE_Gears_Data!$H$2:$H$21)
