Workbook

Sheet Survey_Data
A1: Respondent_ID | B1: Region | C1: Age_Group | D1: Owns_Two_Wheeler | E1: Planning_to_Buy | F1: Loan_Interest | G1: Estimated_Bike_Price | H1: Loan_Amount | I1: Annual_Income
A2: R01 | B2: North | C2: 18-25 | D2: No | E2: Yes | F2: Yes | G2: 90000 | H2: 70000 | I2: 240000
A3: R02 | B3: North | C3: 26-35 | D3: Yes | E3: No | F3: No | G3: 110000 | H3: 0 | I3: 360000
A4: R03 | B4: North | C4: 36-45 | D4: No | E4: Yes | F4: Yes | G4: 125000 | H4: 95000 | I4: 420000
A5: R04 | B5: South | C5: 18-25 | D5: No | E5: Yes | F5: Yes | G5: 85000 | H5: 65000 | I5: 210000
A6: R05 | B6: South | C6: 26-35 | D6: Yes | E6: No | F6: No | G6: 120000 | H6: 0 | I6: 390000
A7: R06 | B7: South | C7: 36-45 | D7: No | E7: Yes | F7: Yes | G7: 135000 | H7: 100000 | I7: 450000
A8: R07 | B8: East | C8: 18-25 | D8: No | E8: Yes | F8: Yes | G8: 80000 | H8: 60000 | I8: 200000
A9: R08 | B9: East | C9: 26-35 | D9: No | E9: Yes | F9: Yes | G9: 100000 | H9: 75000 | I9: 300000
A10: R09 | B10: East | C10: 36-45 | D10: Yes | E10: No | F10: No | G10: 130000 | H10: 0 | I10: 410000
A11: R10 | B11: West | C11: 18-25 | D11: No | E11: Yes | F11: Yes | G11: 95000 | H11: 70000 | I11: 250000
A12: R11 | B12: West | C12: 26-35 | D12: Yes | E12: No | F12: No | G12: 115000 | H12: 0 | I12: 370000
A13: R12 | B13: West | C13: 36-45 | D13: No | E13: Yes | F13: Yes | G13: 140000 | H13: 105000 | I13: 480000
... A16: R15 | B16: Central | C16: 36-45 | D16: Yes | E16: No | F16: No | G16: 128000 | H16: 0 | I16: 400000

Sheet Market_Assumptions
A1: Parameter | B1: Value | C1: Explanation
A2: Target_Population | B2: 1000000 | C2: Illustrative target population
A3: Survey_Sample_Size | B3: 15 | C3: Number of respondents in the sample
A4: Planning_to_Buy_Count | B4: =COUNTIF(Survey_Data!E2:E16,"Yes") | C4: Sample respondents planning to buy
A5: Purchase_Rate | B5: =B4/B3 | C5: Planning-to-buy rate in sample
A6: Estimated_Market_Units | B6: =B2*B5 | C6: Estimated potential two-wheeler buyers
A7: Average_Bike_Price | B7: =AVERAGE(Survey_Data!G2:G16) | C7: Average estimated bike price
A8: Average_Loan_Amount | B8: =AVERAGEIF(Survey_Data!F2:F16,"Yes",Survey_Data!H2:H16) | C8: Average loan among interested respondents
A9: Estimated_Market_Value | B9: =B6*B7 | C9: Potential market value using average bike price
A10: Estimated_Loan_Market | B10: =B6*B8 | C10: Illustrative potential loan amount

Sheet Regional_Analysis
A1: Region | B1: Respondents | C1: Planning_to_Buy | D1: Buy_Rate | E1: Avg_Loan_Amount
A2: North | B2: =COUNTIF(Survey_Data!B2:B16,A2) | C2: =COUNTIFS(Survey_Data!B2:B16,A2,Survey_Data!E2:E16,"Yes") | D2: =IFERROR(C2/B2,0) | E2: =IFERROR(AVERAGEIFS(Survey_Data!H2:H16,Survey_Data!B2:B16,A2,Survey_Data!F2:F16,"Yes"),0)
A3: South | B3: =COUNTIF(Survey_Data!B2:B16,A3) | C3: =COUNTIFS(Survey_Data!B2:B16,A3,Survey_Data!E2:E16,"Yes") | D3: =IFERROR(C3/B3,0) | E3: =IFERROR(AVERAGEIFS(Survey_Data!H2:H16,Survey_Data!B2:B16,A3,Survey_Data!F2:F16,"Yes"),0)
A4: East | B4: =COUNTIF(Survey_Data!B2:B16,A4) | C4: =COUNTIFS(Survey_Data!B2:B16,A4,Survey_Data!E2:E16,"Yes") | D4: =IFERROR(C4/B4,0) | E4: =IFERROR(AVERAGEIFS(Survey_Data!H2:H16,Survey_Data!B2:B16,A4,Survey_Data!F2:F16,"Yes"),0)
A5: West | B5: =COUNTIF(Survey_Data!B2:B16,A5) | C5: =COUNTIFS(Survey_Data!B2:B16,A5,Survey_Data!E2:E16,"Yes") | D5: =IFERROR(C5/B5,0) | E5: =IFERROR(AVERAGEIFS(Survey_Data!H2:H16,Survey_Data!B2:B16,A5,Survey_Data!F2:F16,"Yes"),0)
A6: Central | B6: =COUNTIF(Survey_Data!B2:B16,A6) | C6: =COUNTIFS(Survey_Data!B2:B16,A6,Survey_Data!E2:E16,"Yes") | D6: =IFERROR(C6/B6,0) | E6: =IFERROR(AVERAGEIFS(Survey_Data!H2:H16,Survey_Data!B2:B16,A6,Survey_Data!F2:F16,"Yes"),0)

Sheet Loan_Analysis
A1: Metric | B1: Value
A2: Loan_Interested_Count | B2: =COUNTIF(Survey_Data!F2:F16,"Yes")
A3: Average_Loan_Amount | B3: =AVERAGEIF(Survey_Data!F2:F16,"Yes",Survey_Data!H2:H16)
A4: Minimum_Loan_Amount | B4: =MIN(Survey_Data!H2:H16)
A5: Maximum_Loan_Amount | B5: =MAX(Survey_Data!H2:H16)
A6: Total_Loan_Amount_in_Sample | B6: =SUM(Survey_Data!H2:H16)

Sheet Practice
A1: Task_No | B1: Practice_Task | C1: Expected_Output
A2: 1 | B2: Calculate the number of respondents planning to buy a two-wheeler. | C2: Count
A3: 2 | B3: Calculate the sample purchase rate. | C3: Percentage
A4: 3 | B4: Estimate potential buyers from a target population of 1,000,000. | C4: Estimated units
A5: 4 | B5: Calculate average estimated bike price. | C5: Average
A6: 5 | B6: Estimate potential market value. | C6: Market value
A7: 6 | B7: Compare buy rates across regions. | C7: Regional comparison
A8: 7 | B8: Calculate average loan amount among interested respondents. | C8: Average loan
A9: 8 | B9: Write three business insights from the survey. | C9: 3 insights

Sheet Insights
A1: Insight_Area | B1: Question | C1: Your_Observation
A2: Market Size | B2: What proportion of the sample plans to buy?
A3: Regional Demand | B3: Which region has the highest sample buy rate?
A4: Loan Demand | B4: What is the average loan amount among interested respondents?
A5: Market Value | B5: What does the estimated market value suggest?
A6: Business Decision | B6: What could a two-wheeler lender or manufacturer do with these findings?

Sheet Instructions
A1: Day | B1: Day 011
A2: Lecture | B2: W3_L1 — Estimating Market Size Part 1 — Two-Wheeler Loans & Surveys
A3: Objective | B3: Use survey results and assumptions to estimate a potential market.
A4: Step 1 | B4: Review Survey_Data.
A5: Step 2 | B5: Calculate planning-to-buy rate.
A6: Step 3 | B6: Apply the rate to the target population.
A7: Step 4 | B7: Estimate market value using average bike price.
A8: Step 5 | B8: Analyse regional and loan patterns.
A9: Step 6 | B9: Write business insights in Insights.
