Workbook

Sheet ACE_Gears_Data
A1: Record_ID | B1: Product | C1: Region | D1: Customer_Type | E1: Production_Units | F1: Sales_Units | G1: Scrap_Units | H1: Revenue | I1: Production_Cost
A2: 1 | B2: Gears | C2: North | D2: OEM | E2: 1200 | F2: 950 | G2: 180 | H2: 72000 | I2: 68400
A3: 2 | B3: Gears | C3: South | D3: OEM | E3: 1350 | F3: 1100 | G3: 210 | H3: 81000 | I3: 77000
A4: 3 | B4: Gears | C4: West | D4: Distributor | E4: 980 | F4: 820 | G4: 145 | H4: 58800 | I4: 50840
A5: 4 | B5: Shafts | C5: North | D5: OEM | E5: 900 | F5: 760 | G5: 130 | H5: 54000 | I5: 57760
A6: 5 | B6: Shafts | C6: South | D6: Distributor | E6: 1050 | F6: 880 | G6: 160 | H6: 63000 | I6: 56320
A7: 6 | B7: Shafts | C7: West | D7: OEM | E7: 1120 | F7: 940 | G7: 175 | H7: 67200 | I7: 65800
A8: 7 | B8: Bearings | C8: North | D8: Distributor | E8: 1500 | F8: 1260 | G8: 220 | H8: 75000 | I8: 65520
A9: 8 | B9: Bearings | C9: South | D9: OEM | E9: 1650 | F9: 1400 | G9: 250 | H9: 82500 | I9: 80500
A10: 9 | B10: Bearings | C10: West | D10: Distributor | E10: 1380 | F10: 1160 | G10: 205 | H10: 69000 | I10: 59890
A11: 10 | B11: Gears | C11: North | D11: Distributor | E11: 1280 | F11: 1040 | G11: 195 | H11: 76800 | I11: 71760
A12: 11 | B12: Gears | C12: South | D12: OEM | E12: 1420 | F12: 1180 | G12: 225 | H12: 85200 | I12: 82600
A13: 12 | B13: Gears | C13: West | D13: OEM | E13: 1100 | F13: 920 | G13: 165 | H13: 66000 | I13: 60720
... A21: 20 | B21: Shafts | C21: South | D21: Distributor | E21: 1160 | F21: 950 | G21: 180 | H21: 69600 | I21: 61700

Sheet Background_Context
A1: Topic | B1: Background Context
A2: Case | B2: ACE Gears manufacturing case
A3: Sector | B3: Manufacturing
A4: Business View | B4: Product, regional, customer and operational performance
A5: Products | B5: Gears, Shafts, Bearings
A6: Regions | B6: North, South, West
A7: Customers | B7: OEM, Distributor
A8: Operational Focus | B8: Production, sales and scrap
A9: Financial Focus | B9: Revenue, production cost and gross margin
A10: Analytical Purpose | B10: Understand the case setting before detailed dataset analysis

Sheet Business_Setting
A1: Area | B1: Context
A2: Manufacturing | B2: Production creates physical units that can be sold or recorded as scrap.
A3: Products | B3: Different product categories can have different sales and financial profiles.
A4: Regions | B4: Regional views help compare business performance across locations.
A5: Customers | B5: OEM and Distributor groups represent different customer types.
A6: Revenue | B6: Revenue provides a sales-value perspective.
A7: Cost | B7: Production cost provides a cost perspective.
A8: Quality | B8: Scrap provides an operational-quality perspective.

Sheet Stakeholders
A1: Stakeholder | B1: Possible Information Need
A2: Management | B2: Overall performance and business direction
A3: Sales Team | B3: Product, region and customer sales performance
A4: Production Team | B4: Production volume and scrap
A5: Finance Team | B5: Revenue, cost and margin
A6: Operations Team | B6: Operational efficiency and quality indicators
A7: Business Analyst | B7: Structured evidence for business questions

Sheet Business_Questions
A1: ID | B1: Question | C1: Context
A2: 1 | B2: How is performance distributed across products? | C2: Product context
A3: 2 | B3: How does performance differ by region? | C3: Regional context
A4: 3 | B4: How do OEM and Distributor customers compare? | C4: Customer context
A5: 4 | B5: How do production and sales relate? | C5: Operational context
A6: 5 | B6: What does scrap indicate about production? | C6: Quality context
A7: 6 | B7: How do revenue and production cost compare? | C7: Financial context
A8: 7 | B8: Which areas need deeper investigation? | C8: Decision-support context

Sheet Data_Dictionary
A1: Field | B1: Meaning | C1: Type
A2: Record_ID | B2: Observation identifier | C2: Integer
A3: Product | B3: Manufactured product | C3: Category
A4: Region | B4: Business region | C4: Category
A5: Customer_Type | B5: Customer group | C5: Category
A6: Production_Units | B6: Units produced | C6: Numeric
A7: Sales_Units | B7: Units sold | C7: Numeric
A8: Scrap_Units | B8: Units recorded as scrap | C8: Numeric
A9: Revenue | B9: Recorded revenue | C9: Numeric
A10: Production_Cost | B10: Recorded production cost | C10: Numeric

Sheet Analysis_Roadmap
A1: Stage | B1: Action
A2: 1 | B2: Understand the business background
A3: 2 | B3: Identify products, regions and customer groups
A4: 3 | B4: Understand operational measures
A5: 4 | B5: Understand financial measures
A6: 5 | B6: Inspect data structure
A7: 6 | B7: Build product summaries
A8: 7 | B8: Build regional summaries
A9: 8 | B9: Build customer summaries
A10: 9 | B10: Visualize key comparisons
A11: 10 | B11: Move to detailed case analysis

Sheet Context_Notes
A1: Note | B1: Detail
A2: Scope | B2: Day 040 focuses on background context rather than detailed case calculations.
A3: Dataset | B3: The workbook uses an illustrative learning dataset inspired by the case topic.
A4: Official Data | B4: The sample is not claimed to be the official IITM ACE Gears dataset.
A5: Use | B5: Use the data to practice understanding business context and analytical structure.
A6: Next Step | B6: Detailed dataset introduction and analysis can follow the course sequence.

Sheet Product_Context_Summary
A1: Product | B1: Production Units | C1: Sales Units | D1: Revenue | E1: Production Cost | F1: Gross Margin
A2: Gears | B2: =SUMIF(ACE_Gears_Data!$B$2:$B$21,A2,ACE_Gears_Data!$E$2:$E$21) | C2: =SUMIF(ACE_Gears_Data!$B$2:$B$21,A2,ACE_Gears_Data!$F$2:$F$21) | D2: =SUMIF(ACE_Gears_Data!$B$2:$B$21,A2,ACE_Gears_Data!$H$2:$H$21) | E2: =SUMIF(ACE_Gears_Data!$B$2:$B$21,A2,ACE_Gears_Data!$I$2:$I$21) | F2: =D2-E2
A3: Shafts | B3: =SUMIF(ACE_Gears_Data!$B$2:$B$21,A3,ACE_Gears_Data!$E$2:$E$21) | C3: =SUMIF(ACE_Gears_Data!$B$2:$B$21,A3,ACE_Gears_Data!$F$2:$F$21) | D3: =SUMIF(ACE_Gears_Data!$B$2:$B$21,A3,ACE_Gears_Data!$H$2:$H$21) | E3: =SUMIF(ACE_Gears_Data!$B$2:$B$21,A3,ACE_Gears_Data!$I$2:$I$21) | F3: =D3-E3
A4: Bearings | B4: =SUMIF(ACE_Gears_Data!$B$2:$B$21,A4,ACE_Gears_Data!$E$2:$E$21) | C4: =SUMIF(ACE_Gears_Data!$B$2:$B$21,A4,ACE_Gears_Data!$F$2:$F$21) | D4: =SUMIF(ACE_Gears_Data!$B$2:$B$21,A4,ACE_Gears_Data!$H$2:$H$21) | E4: =SUMIF(ACE_Gears_Data!$B$2:$B$21,A4,ACE_Gears_Data!$I$2:$I$21) | F4: =D4-E4

Sheet Region_Context_Summary
A1: Region | B1: Production Units | C1: Sales Units | D1: Revenue | E1: Production Cost | F1: Gross Margin
A2: North | B2: =SUMIF(ACE_Gears_Data!$C$2:$C$21,A2,ACE_Gears_Data!$E$2:$E$21) | C2: =SUMIF(ACE_Gears_Data!$C$2:$C$21,A2,ACE_Gears_Data!$F$2:$F$21) | D2: =SUMIF(ACE_Gears_Data!$C$2:$C$21,A2,ACE_Gears_Data!$H$2:$H$21) | E2: =SUMIF(ACE_Gears_Data!$C$2:$C$21,A2,ACE_Gears_Data!$I$2:$I$21) | F2: =D2-E2
A3: South | B3: =SUMIF(ACE_Gears_Data!$C$2:$C$21,A3,ACE_Gears_Data!$E$2:$E$21) | C3: =SUMIF(ACE_Gears_Data!$C$2:$C$21,A3,ACE_Gears_Data!$F$2:$F$21) | D3: =SUMIF(ACE_Gears_Data!$C$2:$C$21,A3,ACE_Gears_Data!$H$2:$H$21) | E3: =SUMIF(ACE_Gears_Data!$C$2:$C$21,A3,ACE_Gears_Data!$I$2:$I$21) | F3: =D3-E3
A4: West | B4: =SUMIF(ACE_Gears_Data!$C$2:$C$21,A4,ACE_Gears_Data!$E$2:$E$21) | C4: =SUMIF(ACE_Gears_Data!$C$2:$C$21,A4,ACE_Gears_Data!$F$2:$F$21) | D4: =SUMIF(ACE_Gears_Data!$C$2:$C$21,A4,ACE_Gears_Data!$H$2:$H$21) | E4: =SUMIF(ACE_Gears_Data!$C$2:$C$21,A4,ACE_Gears_Data!$I$2:$I$21) | F4: =D4-E4

Sheet Background_Dashboard
A1: ACE GEARS — BACKGROUND CONTEXT DASHBOARD
A2: Day 040 | Illustrative case-context overview
A4: Product | B4: Revenue
A5: Gears | B5: =SUMIF(ACE_Gears_Data!$B$2:$B$21,A5,ACE_Gears_Data!$H$2:$H$21)
A6: Shafts | B6: =SUMIF(ACE_Gears_Data!$B$2:$B$21,A6,ACE_Gears_Data!$H$2:$H$21)
A7: Bearings | B7: =SUMIF(ACE_Gears_Data!$B$2:$B$21,A7,ACE_Gears_Data!$H$2:$H$21)
A9: Region | B9: Revenue
A10: North | B10: =SUMIF(ACE_Gears_Data!$C$2:$C$21,A10,ACE_Gears_Data!$H$2:$H$21)
A11: South | B11: =SUMIF(ACE_Gears_Data!$C$2:$C$21,A11,ACE_Gears_Data!$H$2:$H$21)
A12: West | B12: =SUMIF(ACE_Gears_Data!$C$2:$C$21,A12,ACE_Gears_Data!$H$2:$H$21)

Sheet Instructions
A1: Step | B1: Instruction
A2: 1 | B2: Read Background_Context.
A3: 2 | B3: Read Business_Setting and Stakeholders.
A4: 3 | B4: Review the Data_Dictionary.
A5: 4 | B5: Inspect the illustrative ACE_Gears_Data.
A6: 5 | B6: Review Product_Context_Summary.
A7: 6 | B7: Review Region_Context_Summary.
A8: 7 | B8: Attempt Business_Questions.
A9: 8 | B9: Use Analysis_Roadmap to prepare for detailed case work.
